meetupscraper/__init__.py
meetupscraper-0.11.2.dist-info/licenses/LICENSE
meetupscraper-0.11.2.dist-info/METADATA
meetupscraper-0.11.2.dist-info/WHEEL
meetupscraper-0.11.2.dist-info/top_level.txt
meetupscraper-0.11.2.dist-info/RECORD
