Metadata-Version: 2.4
Name: meetupscraper
Version: 0.11.2
Summary: A web scraper for meetup.com
Home-page: http://github.com/hakierspejs/meetupscraper
Author: Hakiespejs Łódź
Author-email: d33tah@gmail.com
License: WTFPL
License-File: LICENSE
Requires-Dist: requests
Requires-Dist: lxml
Requires-Dist: python-dateutil
Requires-Dist: icalendar
Dynamic: author
Dynamic: author-email
Dynamic: description
Dynamic: home-page
Dynamic: license
Dynamic: license-file
Dynamic: requires-dist
Dynamic: summary
